jk_hwriter/HWriter.py
jk_hwriter/HWriter2.py
jk_hwriter/TextChunk.py
jk_hwriter/__init__.py
jk_hwriter-0.2025.12.18.dist-info/licenses/LICENSE.txt
jk_hwriter-0.2025.12.18.dist-info/WHEEL
jk_hwriter-0.2025.12.18.dist-info/METADATA
jk_hwriter-0.2025.12.18.dist-info/RECORD
