Metadata-Version: 2.4
Name: jk_hwriter
Version: 0.2025.12.18
Summary: This python module supports writing indented text files.
Keywords: 
Author-email: Jürgen Knauth <pubsrc@binary-overflow.de>
Maintainer-email: Jürgen Knauth <pubsrc@binary-overflow.de>
Requires-Python: >=3.8
Classifier: Development Status :: 5 - Production/Stable
Classifier: License :: OSI Approved :: Apache Software License
Classifier: Programming Language :: Python :: 3
License-File: LICENSE.txt
Requires-Dist: jk_typing
Requires-Dist: jk_prettyprintobj
